osbot_serverless_flows/Serverless_Flows__Server_Config.py
osbot_serverless_flows/Serverless_Flows__Shared_Objects.py
osbot_serverless_flows/__init__.py
osbot_serverless_flows/aws/__init__.py
osbot_serverless_flows/aws/s3/S3_DB__Flows.py
osbot_serverless_flows/aws/s3/__init__.py
osbot_serverless_flows/fast_api/Fast_API__Serverless_Flows.py
osbot_serverless_flows/fast_api/__init__.py
osbot_serverless_flows/fast_api/routes/Routes__Browser.py
osbot_serverless_flows/fast_api/routes/Routes__Debug.py
osbot_serverless_flows/fast_api/routes/Routes__Dev.py
osbot_serverless_flows/fast_api/routes/Routes__GSuite.py
osbot_serverless_flows/fast_api/routes/Routes__Info.py
osbot_serverless_flows/fast_api/routes/__init__.py
osbot_serverless_flows/flows/__init__.py
osbot_serverless_flows/flows/browser/Flow__Playwright__Get_Page_Html.py
osbot_serverless_flows/flows/browser/Flow__Playwright__Get_Page_Pdf.py
osbot_serverless_flows/flows/browser/Flow__Playwright__Get_Page_Screenshot.py
osbot_serverless_flows/flows/browser/__init__.py
osbot_serverless_flows/flows/dev/Flow__Testing_Tasks.py
osbot_serverless_flows/flows/dev/__init__.py
osbot_serverless_flows/flows/gsuite/Flow__GSuite__Create_Presentation.py
osbot_serverless_flows/flows/gsuite/__init__.py
osbot_serverless_flows/flows/http/Flow__Http__Raw_Html.py
osbot_serverless_flows/flows/http/__init__.py
osbot_serverless_flows/lambdas/__init__.py
osbot_serverless_flows/lambdas/handler.py
osbot_serverless_flows/playwright/Playwright__Install_Check.py
osbot_serverless_flows/playwright/Playwright__Serverless.py
osbot_serverless_flows/playwright/__init__.py
osbot_serverless_flows/utils/Version.py
osbot_serverless_flows/utils/__init__.py
osbot_serverless_flows/utils/_for_osbot_aws/Http__Remote_Shell.py
osbot_serverless_flows/utils/_for_osbot_aws/__init__.py
osbot_serverless_flows/version
osbot_serverless_flows-0.15.0.dist-info/LICENSE
osbot_serverless_flows-0.15.0.dist-info/METADATA
osbot_serverless_flows-0.15.0.dist-info/WHEEL
osbot_serverless_flows-0.15.0.dist-info/RECORD
