Metadata-Version: 2.1
Name: osbot_serverless_flows
Version: 0.15.0
Summary: OSBot Serverless Flows
Home-page: https://github.com/owasp-sbot/OSBot-Serverless-Flows
License: MIT
Author: Dinis Cruz
Author-email: dinis.cruz@owasp.org
Requires-Python: >=3.11,<4.0
Classifier: License :: OSI Approved :: MIT License
Classifier: Programming Language :: Python :: 3
Classifier: Programming Language :: Python :: 3.11
Classifier: Programming Language :: Python :: 3.12
Classifier: Programming Language :: Python :: 3.13
Requires-Dist: bs4
Requires-Dist: coverage (>=7.6.1,<8.0.0)
Requires-Dist: httpx
Requires-Dist: mangum
Requires-Dist: oauth2client
Requires-Dist: osbot-aws
Requires-Dist: osbot-fast-api
Requires-Dist: osbot-gsuite
Requires-Dist: osbot-local-stack
Requires-Dist: osbot-prefect
Requires-Dist: osbot-utils
Requires-Dist: osbot_playwright
Requires-Dist: pytest (>=8.3.3,<9.0.0)
Requires-Dist: requests
Project-URL: Repository, https://github.com/owasp-sbot/OSBot-Serverless-Flows
